Metadata-Version: 1.1
Name: weibospider
Version: 0.0.1
Summary: A simple but powerful spider for sinaweibo.For more information or comprehensive instructions, please contact at my email
Home-page: https://github.com/SuperSaiyanSSS/SinaWeiboSpider
Author: wang xiaowei
Author-email: 3233069648@qq.com
License: BSD License
Platform: all
Classifier: Development Status :: 4 - Beta
Classifier: Operating System :: OS Independent
Classifier: Intended Audience :: Developers
Classifier: License :: OSI Approved :: BSD License
Classifier: Programming Language :: Python
Classifier: Programming Language :: Python :: Implementation
Classifier: Programming Language :: Python :: 2
Classifier: Programming Language :: Python :: 2.7
Classifier: Programming Language :: Python :: 3
Classifier: Programming Language :: Python :: 3.4
Classifier: Programming Language :: Python :: 3.5
Classifier: Programming Language :: Python :: 3.6
Classifier: Topic :: Software Development :: Libraries
